anslapi/__init__.py
anslapi/apihandler.py
anslapi-1.0.1.dist-info/LICENSE
anslapi-1.0.1.dist-info/METADATA
anslapi-1.0.1.dist-info/WHEEL
anslapi-1.0.1.dist-info/top_level.txt
anslapi-1.0.1.dist-info/RECORD
