Metadata-Version: 2.1
Name: anslapi
Version: 1.0.1
Summary: Module for creating a simple API with AWS Lambda and API Gateway
Home-page: https://github.com/anttin/anslapi
Author: anttin
Author-email: muut.py@antion.fi
License: UNKNOWN
Platform: UNKNOWN
Classifier: Programming Language :: Python :: 3
Classifier: License :: OSI Approved :: MIT License
Classifier: Operating System :: OS Independent
License-File: LICENSE
